thonny_loaduiautocomplete-0.2.2.data/data/requirements.txt
thonnycontrib/pyqt_loadui_autocomplete/__init__.py
thonny_loaduiautocomplete-0.2.2.dist-info/METADATA
thonny_loaduiautocomplete-0.2.2.dist-info/WHEEL
thonny_loaduiautocomplete-0.2.2.dist-info/top_level.txt
thonny_loaduiautocomplete-0.2.2.dist-info/RECORD
